[
    {
        "id": 1,
        "title": "Continuidad 1",
        "description": "Photo description",
        "category": "continuidad",
        "thumbnail": "https://i.ibb.co/g986tBV/1.png",
        "img": "https://i.ibb.co/XpyxbM7/2.png",
        "sub-category": true
    },
    {
        "id": 6,
        "title": "Continuidad 1",
        "description": "Photo description",
        "category": "continuidad",
        "thumbnail": "https://i.ibb.co/g986tBV/1.png",
        "img": "https://i.ibb.co/sswfqBy/3.png",
        "sub-category": true
    },
    {
        "id": 2,
        "title": "Diario de viaje 1",
        "description": "Photo description",
        "category": "diario de viaje",
        "sub-category": false,
        "thumbnail": "https://i.ibb.co/Xz3qyM6/2.png",
        "img": [
            "https://i.ibb.co/Xz3qyM6/2.png"
        ]
    },
    {
        "id": 3,
        "title": "Fotoperiodismo 1",
        "description": "Photo description",
        "category": "fotoperiodismo",
        "sub-category": false,
        "thumbnail": "https://i.ibb.co/c2yJd4p/3.png",
        "img": [
            "https://cdn.pixabay.com/photo/2015/04/23/22/00/tree-736885_1280.jpg"
        ]
    },
    {
        "id": 4,
        "title": "Mutar 1",
        "description": "Photo description",
        "category": "mutar",
        "sub-category": false,
        "thumbnail": "https://i.ibb.co/2gwHQCD/4.png",
        "img": [
            "https://www.dzoom.org.es/wp-content/uploads/2017/07/seebensee-2384369-810x540.jpg"
        ]
    },
    {
        "id": 5,
        "title": "Retratos 1",
        "description": "Photo description",
        "category": "retratos",
        "sub-category": false,
        "thumbnail": "https://i.ibb.co/J3Zxcmx/5.png",
        "img": [
            "https://static.leonoticias.com/www/multimedia/202107/06/media/MM-senderismo-asturias/oddle-1-ksRC--1350x900@El%20Comercio.jpg"
        ]
    }
]